[{"date": "20231102", "open": 5600.0, "high": 5710.0, "low": 5590.0, "close": 5640.0}, {"date": "20231103", "open": 5700.0, "high": 5720.0, "low": 5610.0, "close": 5690.0}, {"date": "20231106", "open": 5770.0, "high": 6070.0, "low": 5770.0, "close": 6070.0}, {"date": "20231107", "open": 6060.0, "high": 6070.0, "low": 5810.0, "close": 5830.0}, {"date": "20231108", "open": 5910.0, "high": 5970.0, "low": 5760.0, "close": 5760.0}, {"date": "20231109", "open": 5820.0, "high": 5910.0, "low": 5760.0, "close": 5790.0}, {"date": "20231110", "open": 5770.0, "high": 5890.0, "low": 5550.0, "close": 5580.0}, {"date": "20231113", "open": 5690.0, "high": 5700.0, "low": 5500.0, "close": 5580.0}, {"date": "20231114", "open": 5620.0, "high": 5670.0, "low": 5580.0, "close": 5660.0}, {"date": "20231115", "open": 5790.0, "high": 5790.0, "low": 5710.0, "close": 5720.0}, {"date": "20231116", "open": 5720.0, "high": 5760.0, "low": 5680.0, "close": 5700.0}, {"date": "20231117", "open": 5740.0, "high": 5740.0, "low": 5630.0, "close": 5650.0}, {"date": "20231120", "open": 5650.0, "high": 5740.0, "low": 5610.0, "close": 5690.0}, {"date": "20231121", "open": 5750.0, "high": 5780.0, "low": 5690.0, "close": 5730.0}, {"date": "20231122", "open": 5700.0, "high": 5750.0, "low": 5650.0, "close": 5730.0}, {"date": "20231123", "open": 5740.0, "high": 5790.0, "low": 5700.0, "close": 5760.0}, {"date": "20231124", "open": 5790.0, "high": 5810.0, "low": 5710.0, "close": 5750.0}, {"date": "20231127", "open": 5750.0, "high": 5780.0, "low": 5700.0, "close": 5760.0}, {"date": "20231128", "open": 5780.0, "high": 5930.0, "low": 5760.0, "close": 5910.0}, {"date": "20231129", "open": 5940.0, "high": 5940.0, "low": 5770.0, "close": 5790.0}, {"date": "20231130", "open": 5800.0, "high": 5830.0, "low": 5640.0, "close": 5670.0}, {"date": "20231201", "open": 5660.0, "high": 5750.0, "low": 5620.0, "close": 5650.0}, {"date": "20231204", "open": 5680.0, "high": 5770.0, "low": 5620.0, "close": 5710.0}, {"date": "20231205", "open": 5710.0, "high": 5750.0, "low": 5580.0, "close": 5600.0}, {"date": "20231206", "open": 5620.0, "high": 5670.0, "low": 5580.0, "close": 5640.0}, {"date": "20231207", "open": 5580.0, "high": 5610.0, "low": 5490.0, "close": 5570.0}, {"date": "20231208", "open": 5610.0, "high": 5810.0, "low": 5570.0, "close": 5770.0}, {"date": "20231211", "open": 5810.0, "high": 5820.0, "low": 5670.0, "close": 5710.0}, {"date": "20231212", "open": 5760.0, "high": 5860.0, "low": 5740.0, "close": 5790.0}, {"date": "20231213", "open": 5840.0, "high": 5840.0, "low": 5700.0, "close": 5700.0}, {"date": "20231214", "open": 5770.0, "high": 5840.0, "low": 5670.0, "close": 5720.0}, {"date": "20231215", "open": 5700.0, "high": 5800.0, "low": 5700.0, "close": 5710.0}, {"date": "20231218", "open": 5710.0, "high": 5750.0, "low": 5660.0, "close": 5700.0}, {"date": "20231219", "open": 5700.0, "high": 5810.0, "low": 5700.0, "close": 5730.0}, {"date": "20231220", "open": 5790.0, "high": 5810.0, "low": 5730.0, "close": 5810.0}, {"date": "20231221", "open": 5790.0, "high": 5790.0, "low": 5710.0, "close": 5780.0}, {"date": "20231222", "open": 5800.0, "high": 5890.0, "low": 5750.0, "close": 5860.0}, {"date": "20231226", "open": 5890.0, "high": 5940.0, "low": 5810.0, "close": 5840.0}, {"date": "20231227", "open": 5800.0, "high": 5850.0, "low": 5530.0, "close": 5630.0}, {"date": "20231228", "open": 5670.0, "high": 5760.0, "low": 5620.0, "close": 5750.0}]