[{"date": "20250102", "open": 3718.0, "high": 3750.0, "low": 3685.0, "close": 3727.0}, {"date": "20250103", "open": 3727.0, "high": 3829.0, "low": 3727.0, "close": 3741.0}, {"date": "20250106", "open": 3783.0, "high": 3848.0, "low": 3773.0, "close": 3834.0}, {"date": "20250107", "open": 3852.0, "high": 4103.0, "low": 3843.0, "close": 4103.0}, {"date": "20250108", "open": 4103.0, "high": 4275.0, "low": 4029.0, "close": 4275.0}, {"date": "20250109", "open": 4192.0, "high": 4257.0, "low": 3899.0, "close": 3899.0}, {"date": "20250110", "open": 3918.0, "high": 4099.0, "low": 3908.0, "close": 4038.0}, {"date": "20250113", "open": 4048.0, "high": 4099.0, "low": 3983.0, "close": 4071.0}, {"date": "20250114", "open": 4103.0, "high": 4103.0, "low": 3997.0, "close": 4085.0}, {"date": "20250115", "open": 4099.0, "high": 4099.0, "low": 4015.0, "close": 4029.0}, {"date": "20250116", "open": 4057.0, "high": 4094.0, "low": 3997.0, "close": 4080.0}, {"date": "20250117", "open": 4080.0, "high": 4206.0, "low": 4048.0, "close": 4080.0}, {"date": "20250120", "open": 4127.0, "high": 4136.0, "low": 4015.0, "close": 4038.0}, {"date": "20250121", "open": 4043.0, "high": 4103.0, "low": 3918.0, "close": 3945.0}, {"date": "20250122", "open": 3983.0, "high": 4010.0, "low": 3941.0, "close": 3964.0}, {"date": "20250123", "open": 3978.0, "high": 4006.0, "low": 3908.0, "close": 3913.0}, {"date": "20250124", "open": 3969.0, "high": 3969.0, "low": 3764.0, "close": 3848.0}, {"date": "20250131", "open": 3894.0, "high": 4043.0, "low": 3890.0, "close": 3973.0}, {"date": "20250203", "open": 3922.0, "high": 3922.0, "low": 3825.0, "close": 3857.0}, {"date": "20250204", "open": 3880.0, "high": 3978.0, "low": 3880.0, "close": 3885.0}, {"date": "20250205", "open": 3918.0, "high": 3969.0, "low": 3890.0, "close": 3945.0}, {"date": "20250206", "open": 3969.0, "high": 4052.0, "low": 3945.0, "close": 3987.0}, {"date": "20250207", "open": 4010.0, "high": 4090.0, "low": 3997.0, "close": 3997.0}, {"date": "20250210", "open": 3978.0, "high": 3992.0, "low": 3880.0, "close": 3931.0}, {"date": "20250211", "open": 3931.0, "high": 3969.0, "low": 3866.0, "close": 3885.0}, {"date": "20250212", "open": 3894.0, "high": 4136.0, "low": 3894.0, "close": 4103.0}, {"date": "20250213", "open": 4113.0, "high": 4182.0, "low": 4034.0, "close": 4052.0}, {"date": "20250214", "open": 3964.0, "high": 4071.0, "low": 3899.0, "close": 4052.0}, {"date": "20250217", "open": 4052.0, "high": 4117.0, "low": 4006.0, "close": 4108.0}, {"date": "20250218", "open": 4141.0, "high": 4141.0, "low": 4043.0, "close": 4122.0}, {"date": "20250219", "open": 4099.0, "high": 4215.0, "low": 4080.0, "close": 4164.0}, {"date": "20250220", "open": 4159.0, "high": 4182.0, "low": 4080.0, "close": 4090.0}, {"date": "20250221", "open": 4150.0, "high": 4410.0, "low": 4131.0, "close": 4187.0}, {"date": "20250224", "open": 4303.0, "high": 4345.0, "low": 4201.0, "close": 4322.0}, {"date": "20250225", "open": 4327.0, "high": 4327.0, "low": 4215.0, "close": 4229.0}, {"date": "20250226", "open": 4201.0, "high": 4475.0, "low": 4201.0, "close": 4433.0}, {"date": "20250227", "open": 4433.0, "high": 4443.0, "low": 4299.0, "close": 4322.0}, {"date": "20250228", "open": 4261.0, "high": 4336.0, "low": 4117.0, "close": 4117.0}]